cetus_tools/BrokerManager.py
cetus_tools/__init__.py
cetus_tools/binance/BinanceManager.py
cetus_tools/binance/__init__.py
cetus_tools/binance/event/OrderBookProcessing.py
cetus_tools/binance/event/__init__.py
cetus_tools/binance/strategy/BinanceStrategy.py
cetus_tools/binance/strategy/BinanceStrategyActuator.py
cetus_tools/binance/strategy/__init__.py
cetus_tools/binance/strategy/control/OrderAdaptor.py
cetus_tools/binance/strategy/control/SetIcapRatesManager.py
cetus_tools/binance/strategy/control/__init__.py
cetus_tools/binance/strategy/control/adaptors/ForceClosingAdaptor.py
cetus_tools/binance/strategy/control/adaptors/LossAdaptor.py
cetus_tools/binance/strategy/control/adaptors/ProfitAdaptor.py
cetus_tools/binance/strategy/control/adaptors/SecureProfitAdaptor.py
cetus_tools/binance/strategy/control/adaptors/__init__.py
cetus_tools/binance/strategy/control/crud/StrategyCRUD.py
cetus_tools/binance/strategy/control/crud/__init__.py
cetus_tools/bitso/BitsoManager.py
cetus_tools/bitso/__init__.py
cetus_tools/bitso/api/BitsoApiConnection.py
cetus_tools/bitso/api/__init__.py
cetus_tools/bitso/api/tools/__init__.py
cetus_tools/bitso/api/tools/balance.py
cetus_tools/bitso/api/tools/book.py
cetus_tools/bitso/api/tools/order.py
cetus_tools/bitso/api/tools/orderBook.py
cetus_tools/bitso/api/tools/trade.py
cetus_tools/cetus/LogManager.py
cetus_tools/cetus/StrategyApiConnection.py
cetus_tools/cetus/__init__.py
cetus_tools/cetus/data/BinanceMarketDataManager.py
cetus_tools/cetus/data/MarketDataServiceManager.py
cetus_tools/cetus/data/__init__.py
cetus_tools/telegram/TelegramChannelManager.py
cetus_tools/telegram/__init__.py
cetus_tools-0.1.10.dist-info/METADATA
cetus_tools-0.1.10.dist-info/WHEEL
cetus_tools-0.1.10.dist-info/top_level.txt
cetus_tools-0.1.10.dist-info/RECORD
