Metadata-Version: 2.4
Name: cetus_tools
Version: 0.1.10
Summary: Library for python tools used in Cetus developments
Author: Camilo Alaguna
Author-email: camilo.alaguna@itrmachines.com
Keywords: Cetus,Binance,Bitso,Telegram,Public API
Requires-Dist: requests>=2.31.0
Dynamic: author
Dynamic: author-email
Dynamic: description
Dynamic: description-content-type
Dynamic: keywords
Dynamic: requires-dist
Dynamic: summary
